{"window":{"start":"2024-07-29T07:39:00.000Z","end":"2024-07-29T07:40:00.000Z"},"country":"Italy","OPM":1,"total_sale_volume":49.1,"rate_of_return":0.0}
{"window":{"start":"2024-07-28T15:05:00.000Z","end":"2024-07-28T15:06:00.000Z"},"country":"United Kingdom","OPM":14,"total_sale_volume":917.38,"rate_of_return":0.0}
{"window":{"start":"2024-07-27T21:38:00.000Z","end":"2024-07-27T21:39:00.000Z"},"country":"EIRE","OPM":1,"total_sale_volume":2.1,"rate_of_return":0.0}
{"window":{"start":"2024-07-29T02:38:00.000Z","end":"2024-07-29T02:39:00.000Z"},"country":"United Kingdom","OPM":9,"total_sale_volume":485.81000000000006,"rate_of_return":0.0}
{"window":{"start":"2024-07-27T12:04:00.000Z","end":"2024-07-27T12:05:00.000Z"},"country":"United Kingdom","OPM":9,"total_sale_volume":358.33,"rate_of_return":0.0}
{"window":{"start":"2024-07-29T06:08:00.000Z","end":"2024-07-29T06:09:00.000Z"},"country":"United Kingdom","OPM":10,"total_sale_volume":420.19,"rate_of_return":0.1}
{"window":{"start":"2024-07-26T23:25:00.000Z","end":"2024-07-26T23:26:00.000Z"},"country":"United Kingdom","OPM":7,"total_sale_volume":535.44,"rate_of_return":0.14285714285714285}
{"window":{"start":"2024-07-27T17:12:00.000Z","end":"2024-07-27T17:13:00.000Z"},"country":"EIRE","OPM":3,"total_sale_volume":25.900000000000002,"rate_of_return":0.0}
{"window":{"start":"2024-07-27T15:25:00.000Z","end":"2024-07-27T15:26:00.000Z"},"country":"Netherlands","OPM":1,"total_sale_volume":-44.25,"rate_of_return":1.0}
{"window":{"start":"2024-07-28T12:33:00.000Z","end":"2024-07-28T12:34:00.000Z"},"country":"Australia","OPM":1,"total_sale_volume":5.04,"rate_of_return":0.0}
{"window":{"start":"2024-07-28T13:21:00.000Z","end":"2024-07-28T13:22:00.000Z"},"country":"United Kingdom","OPM":12,"total_sale_volume":454.99,"rate_of_return":0.0}
{"window":{"start":"2024-07-27T05:35:00.000Z","end":"2024-07-27T05:36:00.000Z"},"country":"Germany","OPM":1,"total_sale_volume":41.89,"rate_of_return":0.0}
{"window":{"start":"2024-07-27T20:54:00.000Z","end":"2024-07-27T20:55:00.000Z"},"country":"Sweden","OPM":1,"total_sale_volume":239.45,"rate_of_return":0.0}
{"window":{"start":"2024-07-28T04:28:00.000Z","end":"2024-07-28T04:29:00.000Z"},"country":"United Kingdom","OPM":9,"total_sale_volume":527.42,"rate_of_return":0.0}
{"window":{"start":"2024-07-28T22:37:00.000Z","end":"2024-07-28T22:38:00.000Z"},"country":"United Kingdom","OPM":5,"total_sale_volume":281.49,"rate_of_return":0.0}
{"window":{"start":"2024-07-26T17:19:00.000Z","end":"2024-07-26T17:20:00.000Z"},"country":"United Kingdom","OPM":4,"total_sale_volume":298.63,"rate_of_return":0.0}
{"window":{"start":"2024-07-28T05:25:00.000Z","end":"2024-07-28T05:26:00.000Z"},"country":"Germany","OPM":1,"total_sale_volume":17.1,"rate_of_return":0.0}
{"window":{"start":"2024-07-28T18:32:00.000Z","end":"2024-07-28T18:33:00.000Z"},"country":"France","OPM":1,"total_sale_volume":3.9499999999999997,"rate_of_return":0.0}
{"window":{"start":"2024-07-28T05:15:00.000Z","end":"2024-07-28T05:16:00.000Z"},"country":"United Kingdom","OPM":16,"total_sale_volume":80.90999999999998,"rate_of_return":0.1875}
{"window":{"start":"2024-07-28T09:55:00.000Z","end":"2024-07-28T09:56:00.000Z"},"country":"United Kingdom","OPM":8,"total_sale_volume":1086.79,"rate_of_return":0.0}
{"window":{"start":"2024-07-29T05:15:00.000Z","end":"2024-07-29T05:16:00.000Z"},"country":"United Kingdom","OPM":5,"total_sale_volume":-68.67000000000004,"rate_of_return":0.2}
{"window":{"start":"2024-07-27T14:18:00.000Z","end":"2024-07-27T14:19:00.000Z"},"country":"United Kingdom","OPM":11,"total_sale_volume":642.05,"rate_of_return":0.09090909090909091}
{"window":{"start":"2024-07-26T17:49:00.000Z","end":"2024-07-26T17:50:00.000Z"},"country":"United Kingdom","OPM":7,"total_sale_volume":333.42,"rate_of_return":0.14285714285714285}
{"window":{"start":"2024-07-28T09:22:00.000Z","end":"2024-07-28T09:23:00.000Z"},"country":"Norway","OPM":1,"total_sale_volume":16.5,"rate_of_return":0.0}
{"window":{"start":"2024-07-26T20:33:00.000Z","end":"2024-07-26T20:34:00.000Z"},"country":"Germany","OPM":2,"total_sale_volume":93.71,"rate_of_return":0.0}
{"window":{"start":"2024-07-27T16:31:00.000Z","end":"2024-07-27T16:32:00.000Z"},"country":"United Kingdom","OPM":12,"total_sale_volume":689.98,"rate_of_return":0.0}
{"window":{"start":"2024-07-26T15:55:00.000Z","end":"2024-07-26T15:56:00.000Z"},"country":"United Kingdom","OPM":9,"total_sale_volume":311.09,"rate_of_return":0.0}
{"window":{"start":"2024-07-27T12:22:00.000Z","end":"2024-07-27T12:23:00.000Z"},"country":"Germany","OPM":2,"total_sale_volume":217.61000000000004,"rate_of_return":0.0}
{"window":{"start":"2024-07-26T20:25:00.000Z","end":"2024-07-26T20:26:00.000Z"},"country":"France","OPM":1,"total_sale_volume":1800.49,"rate_of_return":0.0}
{"window":{"start":"2024-07-28T11:31:00.000Z","end":"2024-07-28T11:32:00.000Z"},"country":"Germany","OPM":1,"total_sale_volume":11.85,"rate_of_return":0.0}
{"window":{"start":"2024-07-28T12:34:00.000Z","end":"2024-07-28T12:35:00.000Z"},"country":"Spain","OPM":1,"total_sale_volume":148.45999999999998,"rate_of_return":0.0}
{"window":{"start":"2024-07-28T08:25:00.000Z","end":"2024-07-28T08:26:00.000Z"},"country":"EIRE","OPM":1,"total_sale_volume":47.849999999999994,"rate_of_return":0.0}
{"window":{"start":"2024-07-27T20:20:00.000Z","end":"2024-07-27T20:21:00.000Z"},"country":"United Kingdom","OPM":7,"total_sale_volume":790.55,"rate_of_return":0.0}
{"window":{"start":"2024-07-28T12:35:00.000Z","end":"2024-07-28T12:36:00.000Z"},"country":"Unspecified","OPM":1,"total_sale_volume":62.59,"rate_of_return":0.0}
