{"window":{"start":"2024-07-28T07:16:00.000Z","end":"2024-07-28T07:17:00.000Z"},"country":"United Kingdom","OPM":13,"total_sale_volume":668.76,"rate_of_return":0.0}
{"window":{"start":"2024-07-27T09:05:00.000Z","end":"2024-07-27T09:06:00.000Z"},"country":"Germany","OPM":1,"total_sale_volume":45.0,"rate_of_return":0.0}
{"window":{"start":"2024-07-26T20:46:00.000Z","end":"2024-07-26T20:47:00.000Z"},"country":"Portugal","OPM":1,"total_sale_volume":30.119999999999997,"rate_of_return":0.0}
{"window":{"start":"2024-07-26T19:00:00.000Z","end":"2024-07-26T19:01:00.000Z"},"country":"United Kingdom","OPM":6,"total_sale_volume":227.37,"rate_of_return":0.0}
{"window":{"start":"2024-07-28T09:57:00.000Z","end":"2024-07-28T09:58:00.000Z"},"country":"Germany","OPM":1,"total_sale_volume":10.2,"rate_of_return":0.0}
{"window":{"start":"2024-07-28T03:45:00.000Z","end":"2024-07-28T03:46:00.000Z"},"country":"United Kingdom","OPM":5,"total_sale_volume":212.22,"rate_of_return":0.0}
{"window":{"start":"2024-07-27T18:47:00.000Z","end":"2024-07-27T18:48:00.000Z"},"country":"United Kingdom","OPM":8,"total_sale_volume":550.9300000000001,"rate_of_return":0.0}
{"window":{"start":"2024-07-28T10:39:00.000Z","end":"2024-07-28T10:40:00.000Z"},"country":"United Kingdom","OPM":12,"total_sale_volume":363.7999999999999,"rate_of_return":0.08333333333333333}
{"window":{"start":"2024-07-27T22:21:00.000Z","end":"2024-07-27T22:22:00.000Z"},"country":"USA","OPM":1,"total_sale_volume":7.92,"rate_of_return":0.0}
{"window":{"start":"2024-07-27T10:45:00.000Z","end":"2024-07-27T10:46:00.000Z"},"country":"EIRE","OPM":1,"total_sale_volume":25.970000000000002,"rate_of_return":0.0}
{"window":{"start":"2024-07-26T20:57:00.000Z","end":"2024-07-26T20:58:00.000Z"},"country":"Australia","OPM":1,"total_sale_volume":15.8,"rate_of_return":0.0}
{"window":{"start":"2024-07-29T06:42:00.000Z","end":"2024-07-29T06:43:00.000Z"},"country":"United Kingdom","OPM":12,"total_sale_volume":972.9200000000001,"rate_of_return":0.0}
{"window":{"start":"2024-07-27T22:25:00.000Z","end":"2024-07-27T22:26:00.000Z"},"country":"United Kingdom","OPM":10,"total_sale_volume":358.74,"rate_of_return":0.1}
{"window":{"start":"2024-07-27T10:36:00.000Z","end":"2024-07-27T10:37:00.000Z"},"country":"United Kingdom","OPM":3,"total_sale_volume":68.7,"rate_of_return":0.0}
{"window":{"start":"2024-07-28T18:11:00.000Z","end":"2024-07-28T18:12:00.000Z"},"country":"United Kingdom","OPM":11,"total_sale_volume":658.4599999999999,"rate_of_return":0.0}
{"window":{"start":"2024-07-29T06:18:00.000Z","end":"2024-07-29T06:19:00.000Z"},"country":"United Kingdom","OPM":11,"total_sale_volume":1681.96,"rate_of_return":0.0}
{"window":{"start":"2024-07-28T13:42:00.000Z","end":"2024-07-28T13:43:00.000Z"},"country":"Italy","OPM":1,"total_sale_volume":22.28,"rate_of_return":0.0}
{"window":{"start":"2024-07-29T03:01:00.000Z","end":"2024-07-29T03:02:00.000Z"},"country":"EIRE","OPM":1,"total_sale_volume":63.760000000000005,"rate_of_return":0.0}
{"window":{"start":"2024-07-28T00:39:00.000Z","end":"2024-07-28T00:40:00.000Z"},"country":"Singapore","OPM":1,"total_sale_volume":229.00000000000003,"rate_of_return":0.0}
{"window":{"start":"2024-07-27T09:15:00.000Z","end":"2024-07-27T09:16:00.000Z"},"country":"United Kingdom","OPM":9,"total_sale_volume":362.61,"rate_of_return":0.0}
{"window":{"start":"2024-07-28T01:13:00.000Z","end":"2024-07-28T01:14:00.000Z"},"country":"United Kingdom","OPM":10,"total_sale_volume":523.25,"rate_of_return":0.1}
{"window":{"start":"2024-07-29T02:22:00.000Z","end":"2024-07-29T02:23:00.000Z"},"country":"United Kingdom","OPM":9,"total_sale_volume":927.7100000000002,"rate_of_return":0.0}
{"window":{"start":"2024-07-27T05:07:00.000Z","end":"2024-07-27T05:08:00.000Z"},"country":"France","OPM":1,"total_sale_volume":82.72,"rate_of_return":0.0}
{"window":{"start":"2024-07-26T18:02:00.000Z","end":"2024-07-26T18:03:00.000Z"},"country":"United Kingdom","OPM":2,"total_sale_volume":566.42,"rate_of_return":0.0}
{"window":{"start":"2024-07-27T13:40:00.000Z","end":"2024-07-27T13:41:00.000Z"},"country":"United Kingdom","OPM":11,"total_sale_volume":71.14999999999999,"rate_of_return":0.09090909090909091}
{"window":{"start":"2024-07-27T04:01:00.000Z","end":"2024-07-27T04:02:00.000Z"},"country":"United Kingdom","OPM":13,"total_sale_volume":1029.79,"rate_of_return":0.07692307692307693}
